remove_the_bg/__init__.py
remove_the_bg/cli.py
remove_the_bg/core.py
remove_the_bg/vendor/README.md
remove_the_bg/vendor/__init__.py
remove_the_bg/vendor/onnxruntime/LICENSE
remove_the_bg/vendor/onnxruntime/Privacy.md
remove_the_bg/vendor/onnxruntime/ThirdPartyNotices.txt
remove_the_bg/vendor/onnxruntime/__init__.py
remove_the_bg/vendor/onnxruntime/__pycache__/__init__.cpython-39.pyc
remove_the_bg/vendor/onnxruntime/backend/__init__.py
remove_the_bg/vendor/onnxruntime/backend/backend.py
remove_the_bg/vendor/onnxruntime/backend/backend_rep.py
remove_the_bg/vendor/onnxruntime/backend/__pycache__/__init__.cpython-39.pyc
remove_the_bg/vendor/onnxruntime/backend/__pycache__/backend.cpython-39.pyc
remove_the_bg/vendor/onnxruntime/backend/__pycache__/backend_rep.cpython-39.pyc
remove_the_bg/vendor/onnxruntime/capi/__init__.py
remove_the_bg/vendor/onnxruntime/capi/_ld_preload.py
remove_the_bg/vendor/onnxruntime/capi/_pybind_state.py
remove_the_bg/vendor/onnxruntime/capi/onnxruntime.dll
remove_the_bg/vendor/onnxruntime/capi/onnxruntime_collect_build_info.py
remove_the_bg/vendor/onnxruntime/capi/onnxruntime_inference_collection.py
remove_the_bg/vendor/onnxruntime/capi/onnxruntime_providers_shared.dll
remove_the_bg/vendor/onnxruntime/capi/onnxruntime_pybind11_state.pyd
remove_the_bg/vendor/onnxruntime/capi/onnxruntime_validation.py
remove_the_bg/vendor/onnxruntime/capi/version_info.py
remove_the_bg/vendor/onnxruntime/capi/__pycache__/__init__.cpython-39.pyc
remove_the_bg/vendor/onnxruntime/capi/__pycache__/_ld_preload.cpython-39.pyc
remove_the_bg/vendor/onnxruntime/capi/__pycache__/_pybind_state.cpython-39.pyc
remove_the_bg/vendor/onnxruntime/capi/__pycache__/onnxruntime_collect_build_info.cpython-39.pyc
remove_the_bg/vendor/onnxruntime/capi/__pycache__/onnxruntime_inference_collection.cpython-39.pyc
remove_the_bg/vendor/onnxruntime/capi/__pycache__/onnxruntime_validation.cpython-39.pyc
remove_the_bg/vendor/onnxruntime/capi/__pycache__/version_info.cpython-39.pyc
remove_the_bg-1.1.2.dist-info/licenses/LICENSE
remove_the_bg-1.1.2.dist-info/METADATA
remove_the_bg-1.1.2.dist-info/WHEEL
remove_the_bg-1.1.2.dist-info/entry_points.txt
remove_the_bg-1.1.2.dist-info/top_level.txt
remove_the_bg-1.1.2.dist-info/RECORD
